swh/__init__.py
swh/loader/__init__.py
swh/loader/svn/__init__.py
swh/loader/svn/converters.py
swh/loader/svn/exception.py
swh/loader/svn/loader.py
swh/loader/svn/py.typed
swh/loader/svn/replay.py
swh/loader/svn/svn_repo.py
swh/loader/svn/svn_retry.py
swh/loader/svn/tasks.py
swh/loader/svn/utils.py
swh/loader/svn/tests/__init__.py
swh/loader/svn/tests/conftest.py
swh/loader/svn/tests/test_converters.py
swh/loader/svn/tests/test_externals.py
swh/loader/svn/tests/test_loader.org
swh/loader/svn/tests/test_loader.py
swh/loader/svn/tests/test_svn_repo.py
swh/loader/svn/tests/test_svn_retry.py
swh/loader/svn/tests/test_task.py
swh/loader/svn/tests/test_utils.py
swh/loader/svn/tests/utils.py
swh/loader/svn/tests/data/httthttt.tgz
swh/loader/svn/tests/data/mediawiki-repo-r407-eol-native-crlf.tgz
swh/loader/svn/tests/data/penguinsdbtools2018.dump.gz
swh/loader/svn/tests/data/pkg-doc-linux-r10.tgz
swh/loader/svn/tests/data/pkg-doc-linux-r11.tgz
swh/loader/svn/tests/data/pkg-doc-linux-r12.tgz
swh/loader/svn/tests/data/pkg-gourmet-add-remove-dir.tgz
swh/loader/svn/tests/data/pkg-gourmet-tampered-rev6-log.tgz
swh/loader/svn/tests/data/pkg-gourmet-with-edge-case-links-and-files.tgz
swh/loader/svn/tests/data/pkg-gourmet-with-external-id.tgz
swh/loader/svn/tests/data/pkg-gourmet-with-updates.tgz
swh/loader/svn/tests/data/pkg-gourmet-with-wrong-link-cases.tgz
swh/loader/svn/tests/data/pkg-gourmet.tgz
swh/loader/svn/tests/data/pyang-repo-r343-eol-native-mixed-lf-crlf.tgz
swh.loader.svn-1.6.0.dist-info/AUTHORS
swh.loader.svn-1.6.0.dist-info/LICENSE
swh.loader.svn-1.6.0.dist-info/METADATA
swh.loader.svn-1.6.0.dist-info/WHEEL
swh.loader.svn-1.6.0.dist-info/entry_points.txt
swh.loader.svn-1.6.0.dist-info/top_level.txt
swh.loader.svn-1.6.0.dist-info/RECORD
