Metadata-Version: 2.1
Name: swh.loader.svn
Version: 1.6.0
Summary: Software Heritage Loader SVN
Home-page: https://forge.softwareheritage.org/diffusion/DLDSVN
Author: Software Heritage developers
Author-email: swh-devel@inria.fr
Project-URL: Bug Reports, https://forge.softwareheritage.org/maniphest
Project-URL: Funding, https://www.softwareheritage.org/donate
Project-URL: Source, https://forge.softwareheritage.org/source/swh-loader-svn
Project-URL: Documentation, https://docs.softwareheritage.org/devel/swh-loader-svn/
Classifier: Programming Language :: Python :: 3
Classifier: Intended Audience :: Developers
Classifier: License :: OSI Approved :: GNU General Public License v3 (GPLv3)
Classifier: Operating System :: OS Independent
Classifier: Development Status :: 5 - Production/Stable
Requires-Python: >=3.7
License-File: LICENSE
License-File: AUTHORS
Requires-Dist: click
Requires-Dist: iso8601
Requires-Dist: subvertpy (>=0.9.4)
Requires-Dist: tenacity (>=6.2)
Requires-Dist: typing-extensions
Requires-Dist: swh.storage (>=0.11.3)
Requires-Dist: swh.model (>=6.6.0)
Requires-Dist: swh.scheduler (>=0.0.39)
Requires-Dist: swh.loader.core (>=5.0.0)
Provides-Extra: testing
Requires-Dist: pytest ; extra == 'testing'
Requires-Dist: pytest-mock ; extra == 'testing'
Requires-Dist: pytest-postgresql ; extra == 'testing'
Requires-Dist: swh.core[http] (>=0.0.61) ; extra == 'testing'
Requires-Dist: types-click ; extra == 'testing'
Requires-Dist: types-python-dateutil ; extra == 'testing'
